rb_message_writer/__init__.py
rb_message_writer/bigquery_writer.py
rb_message_writer/message_writer.py
rb_message_writer/multi_writer.py
rb_message_writer/sql_writer.py
rb_message_writer-0.1.1.dist-info/LICENSE
rb_message_writer-0.1.1.dist-info/METADATA
rb_message_writer-0.1.1.dist-info/WHEEL
rb_message_writer-0.1.1.dist-info/top_level.txt
rb_message_writer-0.1.1.dist-info/RECORD
